{
    "version": "https://jsonfeed.org/version/1",
    "title": "Sidey",
    "home_page_url": "http://localhost:4000/",
    "feed_url": "http://localhost:4000/feed.json",
    "description": "Simple and minimalistic jekyll blogging theme.",
    "icon": "http://localhost:4000/apple-touch-icon.png",
    "favicon": "http://localhost:4000/favicon.ico",
    "expired": false,
    
    "author": "{"twitter"=>"mrprajesh", "name"=>nil, "avatar"=>nil, "email"=>nil, "url"=>nil}",
    
"items": [
    
        {
            "id": "http://localhost:4000/2020/03/09/helloworld",
            "title": "Hello World",
            "summary": null,
            "content_text": "This is my first post in Github.ioblog.",
            "content_html": "<p>This is my first post in <a href=\"https://mrprajesh.github.io/blog\">Github.io</a>blog.</p>",
            "url": "http://localhost:4000/2020/03/09/helloworld",
            
            
            
            
            
            "date_published": "2020-03-09T00:00:00+05:30",
            "date_modified": "2020-03-09T00:00:00+05:30",
            
                "author": 
                "{"twitter"=>"mrprajesh", "name"=>nil, "avatar"=>nil, "email"=>nil, "url"=>nil}"
                
            
        }
    
    ]
}